{
  "users": {
    "test1": {
      "ratings": {
        "372058": 10
      },
      "created_at": "2025-09-05T16:36:07.445849",
      "last_login": "2025-09-05T18:27:44.530450",
      "total_movies_rated": 1
    },
    "test2": {
      "ratings": {
        "372058": 2,
        "129": 10,
        "378064": 9,
        "526896": 1,
        "652837": 9,
        "476292": 9,
        "530079": 9,
        "568160": 9,
        "667520": 9,
        "572154": 10,
        "204436": 1,
        "508442": 7,
        "533514": 10,
        "291270": 1,
        "100271": 10,
        "11970": 1
      },
      "created_at": "2025-09-05T17:11:54.015294",
      "last_login": "2025-09-05T18:11:08.405235",
      "total_movies_rated": 16
    },
    "test3": {
      "ratings": {
        "372058": 10,
        "299534": 10,
        "299536": 9
      },
      "created_at": "2025-09-05T17:23:47.637777",
      "last_login": "2025-09-05T20:46:26.426315",
      "total_movies_rated": 3
    },
    "test4": {
      "ratings": {
        "299534": 10,
        "299536": 10,
        "27205": 10,
        "100402": 10
      },
      "created_at": "2025-09-05T17:27:24.005760",
      "last_login": "2025-09-05T17:27:24.005768",
      "total_movies_rated": 4
    },
    "test5": {
      "ratings": {
        "372058": 7,
        "324857": 10,
        "557": 10,
        "315635": 7,
        "129": 8
      },
      "created_at": "2025-09-05T17:28:20.842041",
      "last_login": "2025-09-05T17:28:20.842049",
      "total_movies_rated": 5
    },
    "test6": {
      "ratings": {
        "24428": 9
      },
      "created_at": "2025-09-05T20:46:35.702265",
      "last_login": "2025-09-05T20:46:35.702274",
      "total_movies_rated": 1
    }
  },
  "metadata": {
    "total_users": 6,
    "created_at": "2025-09-04T22:04:55.841232"
  }
}